pebblenet/__init__.py
pebblenet/Maryland/__init__.py
pebblenet/Maryland/bay_data.py
pebblenet/Maryland/eotb_data.py
pebblenet/Maryland/noaa_data.py
pebblenet-0.1.3.dist-info/METADATA
pebblenet-0.1.3.dist-info/WHEEL
pebblenet-0.1.3.dist-info/licenses/LICENSE
pebblenet-0.1.3.dist-info/RECORD
