Metadata-Version: 2.4
Name: pebblenet
Version: 0.1.3
Summary: A Python program that retrieves relevant data from the web and structures it in a JSON-compatible format for use in my UUT project.
Project-URL: Homepage, https://github.com/dawnandrew100/pebblenet
Project-URL: Issues, https://github.com/dawnandrew100/pebblenet/issues
Author-email: Andrew Hennis <andrew.mr.hennis@gmail.com>
License-Expression: MIT
License-File: LICENSE
Classifier: License :: OSI Approved :: MIT License
Classifier: Operating System :: OS Independent
Classifier: Programming Language :: Python :: 3
Requires-Python: >=3.9
Requires-Dist: bs4
